loader/__init__.py
loader/config.py
loader/loader.py
django_loader-0.0.14.dist-info/LICENSE
django_loader-0.0.14.dist-info/LICENSE.rst
django_loader-0.0.14.dist-info/LICENSE.rst~
django_loader-0.0.14.dist-info/LICENSE~
django_loader-0.0.14.dist-info/METADATA
django_loader-0.0.14.dist-info/WHEEL
django_loader-0.0.14.dist-info/entry_points.txt
django_loader-0.0.14.dist-info/RECORD
