Metadata-Version: 2.1
Name: django-loader
Version: 0.0.14
Summary: a configuration and secret loader for Django
Home-page: https://github.com/jeremyagray/django-loader
License: MIT
Author: Jeremy A Gray
Author-email: gray@flyquackswim.com
Maintainer: Jeremy A Gray
Maintainer-email: gray@flyquackswim.com
Requires-Python: >=3.10.1,<4.0
Classifier: Development Status :: 3 - Alpha
Classifier: Environment :: Console
Classifier: Framework :: Django :: 5.0
Classifier: Intended Audience :: Developers
Classifier: License :: OSI Approved :: MIT License
Classifier: Programming Language :: Python :: 3
Classifier: Programming Language :: Python :: 3.11
Classifier: Programming Language :: Python :: 3.12
Classifier: Programming Language :: Python :: 3.10
Classifier: Topic :: Internet :: WWW/HTTP :: Site Management
Requires-Dist: Django (>=5.0,<5.1)
Requires-Dist: bespon (>=0)
Requires-Dist: ruamel.yaml (>=0)
Requires-Dist: toml (>=0)
Project-URL: Documentation, https://django-loader.readthedocs.io/
Project-URL: Issues, https://github.com/jeremyagray/django-loader/issues
Project-URL: Repository, https://github.com/jeremyagray/django-loader
